hub/__init__.py
hub/client.py
hub/version.py
hub/db/__init__.py
hub/db/dynamo.py
hub/kinesis/__init__.py
hub/kinesis/data_kinesis.py
hub/kinesis/decorators.py
hub/kinesis/helpers.py
hub/kinesis/listener.py
hub/kinesis/producer.py
hub/workers/__init__.py
hub/workers/worker.py
hub_kinesis-1.0.20.dist-info/METADATA
hub_kinesis-1.0.20.dist-info/WHEEL
hub_kinesis-1.0.20.dist-info/top_level.txt
hub_kinesis-1.0.20.dist-info/RECORD
