Metadata-Version: 2.1
Name: hub-kinesis
Version: 1.0.20
Summary: Library for Kinesis Implementation
Home-page: https://github.com/cuenca-mx/hub
Author: Cuenca
Author-email: dev@cuenca.com
License: UNKNOWN
Platform: UNKNOWN
Classifier: Programming Language :: Python :: 3
Classifier: Programming Language :: Python :: 3.6
Classifier: Programming Language :: Python :: 3.7
Classifier: License :: OSI Approved :: MIT License
Classifier: Operating System :: OS Independent
Requires-Python: >=3.6
Requires-Dist: boto3 (<2.0,>=1.9.84)
Requires-Dist: botocore
Provides-Extra: test
Requires-Dist: pytest ; extra == 'test'
Requires-Dist: pytest-cov ; extra == 'test'
Requires-Dist: black ; extra == 'test'
Requires-Dist: isort[pipfile] ; extra == 'test'
Requires-Dist: flake8 ; extra == 'test'
Requires-Dist: moto (==1.3.13) ; extra == 'test'
